geomapzw/__init__.py
geomapzw/geomapzw.py
geomapzw-0.0.3.dist-info/LICENSE
geomapzw-0.0.3.dist-info/METADATA
geomapzw-0.0.3.dist-info/WHEEL
geomapzw-0.0.3.dist-info/dependency_links.txt
geomapzw-0.0.3.dist-info/top_level.txt
geomapzw-0.0.3.dist-info/RECORD
