Metadata-Version: 2.1
Name: geomapzw
Version: 0.0.3
Summary: This package is for generating web maps
Home-page: https://github.com/faraigit/geomapzw
Author: Farai Maxwell Marumbwa
Author-email: faraimax@gmail.com
License: MIT license
Keywords: geomapzw
Platform: UNKNOWN
Classifier: Development Status :: 2 - Pre-Alpha
Classifier: Intended Audience :: Developers
Classifier: License :: OSI Approved :: MIT License
Classifier: Natural Language :: English
Classifier: Programming Language :: Python :: 3
Classifier: Programming Language :: Python :: 3.5
Classifier: Programming Language :: Python :: 3.6
Classifier: Programming Language :: Python :: 3.7
Classifier: Programming Language :: Python :: 3.8
Requires-Python: >=3.5
Requires-Dist: folium
Requires-Dist: ipyleaflet
